{
    "build": {
	"dockerfile":"Dockerfile"
	},
    "features": {
        "ghcr.io/devcontainers/features/docker-in-docker:2": {},
        "ghcr.io/devcontainers/features/azure-cli:1": {},
		"ghcr.io/devcontainers/features/common-utils:2": {
            "username": "node",
			"userUid": "1000",
			"userGid": "1000"
		},
		"ghcr.io/devcontainers/features/node:1": {}
    },
    "postCreateCommand": "npm install -g @devcontainers/cli",
    "customizations": {
        "vscode": {
            "extensions": [
                "mads-hartmann.bash-ide-vscode",
                "dbaeumer.vscode-eslint",
                "EditorConfig.EditorConfig"
            ]
        }
    },
    "remoteUser":"node"
}
